ndd_test4p/__init__.py
ndd_test4p/comparators.py
ndd_test4p/differences_viewers.py
ndd_test4p/test_cases.py
ndd_test4p/expects/__init__.py
ndd_test4p/expects/content_matchers.py
ndd_test4p/expects/numeric_matchers.py
ndd_test4p-0.4.5.dist-info/AUTHORS.rst
ndd_test4p-0.4.5.dist-info/LICENSE.txt
ndd_test4p-0.4.5.dist-info/METADATA
ndd_test4p-0.4.5.dist-info/WHEEL
ndd_test4p-0.4.5.dist-info/top_level.txt
ndd_test4p-0.4.5.dist-info/RECORD
