Metadata-Version: 2.1
Name: ndd-test4p
Version: 0.4.5
Summary: Utilities for testing Python code
Home-page: https://gitlab.com/ddidier/python-ndd-test4p/
Author: David DIDIER
Author-email: c_inconnu2@yahoo.fr
License: mit
Project-URL: Documentation, https://ddidier.gitlab.io/python-ndd-test4p/
Platform: any
Classifier: Development Status :: 4 - Beta
Classifier: Programming Language :: Python
Classifier: Topic :: Software Development :: Testing
Requires-Dist: expects (>=0.9.0)
Requires-Dist: pyyaml (>=3.13)
Provides-Extra: distributing
Requires-Dist: twine (==3.1.1) ; extra == 'distributing'
Requires-Dist: wheel (==0.34.2) ; extra == 'distributing'
Provides-Extra: documenting
Requires-Dist: sphinx (==2.4.4) ; extra == 'documenting'
Requires-Dist: sphinx-rtd-theme (==0.4.3) ; extra == 'documenting'
Requires-Dist: sphinx-prompt (==1.1.0) ; extra == 'documenting'
Provides-Extra: testing
Requires-Dist: flake8 (==3.7.9) ; extra == 'testing'
Requires-Dist: pylint (==2.4.4) ; extra == 'testing'
Requires-Dist: pytest (==5.4.1) ; extra == 'testing'
Requires-Dist: pytest-cov (==2.8.1) ; extra == 'testing'
Requires-Dist: pytest-mock (==3.1.0) ; extra == 'testing'
Requires-Dist: tox (==3.14.6) ; extra == 'testing'
